MANIFEST.in
README.rst
requirements.txt
setup.py
trackmac/__init__.py
trackmac/app.py
trackmac/cocoa.py
trackmac/config.py
trackmac/main.py
trackmac/models.py
trackmac/utils.py
trackmac.egg-info/PKG-INFO
trackmac.egg-info/SOURCES.txt
trackmac.egg-info/dependency_links.txt
trackmac.egg-info/entry_points.txt
trackmac.egg-info/requires.txt
trackmac.egg-info/top_level.txt