Metadata-Version: 1.0
Name: trackmac
Version: 0.0.4
Summary: A command-line tool to track application usage for OS X
Home-page: http://github.com/MacLeek/trackmac
Author: MacLeek
Author-email: inaoqi@gmail.com
License: MIT
Platform: UNKNOWN
